topsis/topsis.py
Topsis_RounakTaneja_101903784-5.0.0.dist-info/LICENSE
Topsis_RounakTaneja_101903784-5.0.0.dist-info/METADATA
Topsis_RounakTaneja_101903784-5.0.0.dist-info/WHEEL
Topsis_RounakTaneja_101903784-5.0.0.dist-info/entry_points.txt
Topsis_RounakTaneja_101903784-5.0.0.dist-info/top_level.txt
Topsis_RounakTaneja_101903784-5.0.0.dist-info/RECORD
