Metadata-Version: 2.1
Name: Topsis-RounakTaneja-101903784
Version: 5.0.0
Summary: It gives a csv file that includes the topsis result
Home-page: UNKNOWN
Author: Rounak Taneja
Author-email: rtaneja_be19@thapar.edu
License: MIT
Platform: UNKNOWN
Classifier: License :: OSI Approved :: MIT License
Classifier: Programming Language :: Python :: 3.6
Classifier: Programming Language :: Python :: 3.7
Classifier: Programming Language :: Python :: 3.8
Classifier: Programming Language :: Python :: 3.8
Classifier: Programming Language :: Python :: 3.9
Requires-Dist: pandas
Requires-Dist: numpy
